step_machine/__init__.py
step_machine/backend.py
step_machine/cli.py
step_machine/config.py
step_machine/core.py
step_machine/progress.py
step_machine/script.py
step_machine/target.py
step_machine/types.py
step_machine/backends/__init__.py
step_machine/backends/core.py
step_machine/backends/file.py
step_machine/backends/pg.py
step_machine/templates/__init__.py
step_machine/templates/post_validate.py
step_machine/templates/pre_check.py
step_machine/templates/up.py
step_machine/utils/__init__.py
step_machine/utils/jinja2.py
step_machine/utils/peewee.py
step_machine/utils/userdata.py
step_machine-0.0.2.dist-info/METADATA
step_machine-0.0.2.dist-info/WHEEL
step_machine-0.0.2.dist-info/entry_points.txt
step_machine-0.0.2.dist-info/RECORD
